eazylogger/__init__.py
eazylogger/core/__init__.py
eazylogger/core/logger.py
eazylogger-24.9.27.dist-info/METADATA
eazylogger-24.9.27.dist-info/WHEEL
eazylogger-24.9.27.dist-info/top_level.txt
eazylogger-24.9.27.dist-info/RECORD
