Metadata-Version: 2.1
Name: eazylogger
Version: 24.9.27
Summary: A simple module to add color to Python log messages.
Author: Aric Kraft
Project-URL: Homepage, https://github.com/aeazy/eazylogger
Project-URL: Issues, https://github.com/aeazy/eazylogger/issues
Classifier: Programming Language :: Python :: 3
Classifier: License :: OSI Approved :: MIT License
Requires-Python: >=3.11
